{"symbol":"marico","financialData":{"2020":{"FINANCIAL_POSITION":{"ppe":646.7,"inProgressCapWork":"","currentAsset":4113.5,"cashAndEquivalent":420.4,"nonCurrentAsset":894.5,"totalAsset":5008,"totalEquity":1387.6,"currentLiability":3366.7,"nonCurrentLiability":253.5,"totalLiability":3620.2,"longTermLoan":0,"shortTermLoan":0,"currentLongTermLoan":0,"capitalEmployed":"","capitalInvested":"","nav":44.05,"totalShares":31500000,"numericMultiple":1000000},"INCOME_EXPENSE":{"revenue":9795.9,"grossProfit":5671.5,"operatingProfit":3378.8,"profitBeforeTax":3572,"financeCost":46.4,"netProfit":2629.9,"eps":84.01,"costofDA":132.1,"dividend":95,"numericMultiple":1000000},"CASH_FLOW":{"opCashFlow":3613.5,"netOpCashFlow":3012.9,"capex":320.2,"nocfps":95.65,"numericMultiple":1000000}},"2021":{"FINANCIAL_POSITION":{"ppe":771.8,"inProgressCapWork":"","currentAsset":4120.6,"cashAndEquivalent":396.4,"nonCurrentAsset":1673.3,"totalAsset":5793.9,"totalEquity":1636.5,"currentLiability":4002.8,"nonCurrentLiability":154.5,"totalLiability":4157.3,"longTermLoan":0,"shortTermLoan":0,"currentLongTermLoan":0,"capitalEmployed":"","capitalInvested":"","nav":51.95,"totalShares":"","numericMultiple":1000000},"INCOME_EXPENSE":{"revenue":11306.5,"grossProfit":6667.7,"operatingProfit":4284.7,"profitBeforeTax":4194.4,"financeCost":18.9,"netProfit":3083.9,"eps":98.69,"costofDA":115.6,"dividend":90,"numericMultiple":1000000},"CASH_FLOW":{"opCashFlow":4207.7,"netOpCashFlow":3304.6,"capex":241.5,"nocfps":104.91,"numericMultiple":1000000}},"2022":{"FINANCIAL_POSITION":{"ppe":981,"inProgressCapWork":"","currentAsset":5672.6,"cashAndEquivalent":505.1,"nonCurrentAsset":1375,"totalAsset":7047.6,"totalEquity":2689,"currentLiability":4236.2,"nonCurrentLiability":122.3,"totalLiability":4358.5,"longTermLoan":0,"shortTermLoan":0,"currentLongTermLoan":0,"capitalEmployed":"","capitalInvested":"","nav":85.37,"totalShares":"","numericMultiple":1000000},"INCOME_EXPENSE":{"revenue":13032.1,"grossProfit":7071.4,"operatingProfit":4644.3,"profitBeforeTax":4497.2,"financeCost":37,"netProfit":3572.4,"eps":112.82,"costofDA":166.2,"dividend":80,"numericMultiple":1000000},"CASH_FLOW":{"opCashFlow":4457.7,"netOpCashFlow":3605.3,"capex":313.7,"nocfps":114.46,"numericMultiple":1000000}},"2023":{"FINANCIAL_POSITION":{"ppe":1304.6,"inProgressCapWork":"","currentAsset":9970.3,"cashAndEquivalent":2228.8,"nonCurrentAsset":1665.6,"totalAsset":11635.9,"totalEquity":3586.3,"currentLiability":7976.5,"nonCurrentLiability":73,"totalLiability":8049.5,"longTermLoan":0,"shortTermLoan":0,"currentLongTermLoan":0,"capitalEmployed":"","capitalInvested":"","nav":113.85,"totalShares":"","numericMultiple":1000000},"INCOME_EXPENSE":{"revenue":14135.7,"grossProfit":7324.5,"operatingProfit":5137.8,"profitBeforeTax":5031.6,"financeCost":0,"netProfit":3889.7,"eps":122.93,"costofDA":173,"dividend":75,"numericMultiple":1000000},"CASH_FLOW":{"opCashFlow":6200.1,"netOpCashFlow":5393.9,"capex":517.3,"nocfps":171.23,"numericMultiple":1000000}},"2024":{"FINANCIAL_POSITION":{"ppe":1414.6,"inProgressCapWork":"","currentAsset":15014,"cashAndEquivalent":1887.1,"nonCurrentAsset":1892.7,"totalAsset":16906.8,"totalEquity":8210,"currentLiability":8521.1,"nonCurrentLiability":175.6,"totalLiability":8696.7,"longTermLoan":0,"shortTermLoan":0,"currentLongTermLoan":0,"capitalEmployed":"","capitalInvested":"","nav":260.6,"totalShares":"","numericMultiple":1000000},"INCOME_EXPENSE":{"revenue":14524.1,"grossProfit":8424.9,"operatingProfit":6150.8,"profitBeforeTax":5856.6,"financeCost":565.8,"netProfit":4623.7,"eps":146.23,"costofDA":210.1,"dividend":20,"numericMultiple":1000000},"CASH_FLOW":{"opCashFlow":7222.7,"netOpCashFlow":6150.3,"capex":243.7,"nocfps":195.25,"numericMultiple":1000000}}}}